database/__init__.py
database/database.py
tndb-0.0.1.dist-info/METADATA
tndb-0.0.1.dist-info/WHEEL
tndb-0.0.1.dist-info/top_level.txt
tndb-0.0.1.dist-info/RECORD
