Metadata-Version: 2.1
Name: tndb
Version: 0.0.1
Summary: mysql与pgsql集合
Author: tianna
